cdk_wordpress/__init__.py
cdk_wordpress/py.typed
cdk_wordpress/_jsii/__init__.py
cdk_wordpress/_jsii/cdk-wordpress@0.0.1000.jsii.tgz
cdk_wordpress-0.0.1000.dist-info/LICENSE
cdk_wordpress-0.0.1000.dist-info/METADATA
cdk_wordpress-0.0.1000.dist-info/WHEEL
cdk_wordpress-0.0.1000.dist-info/top_level.txt
cdk_wordpress-0.0.1000.dist-info/RECORD
